[{"authors":["admin"],"categories":null,"content":"goal: save time by letting bots \u0026amp; language technology do some of our mental work\nprojects:\n","date":-62135596800,"expirydate":-62135596800,"kind":"taxonomy","lang":"en","lastmod":-62135596800,"objectID":"2525497d367e79493fd32b198b28f040","permalink":"https://owenburton.github.io/author/owen-burton/","publishdate":"0001-01-01T00:00:00Z","relpermalink":"/author/owen-burton/","section":"authors","summary":"goal: save time by letting bots \u0026amp; language technology do some of our mental work\nprojects:","tags":null,"title":"owen burton","type":"authors"}]